napari_bleach_correct/__init__.py
napari_bleach_correct/_button_grid.py
napari_bleach_correct/_dock_widget.py
napari_bleach_correct/_plot_widget.py
napari_bleach_correct/_sample_data.py
napari_bleach_correct/_widgets.py
napari_bleach_correct/napari.yaml
napari_bleach_correct/_tests/__init__.py
napari_bleach_correct/_tests/test_dock_widget.py
napari_bleach_correct/_tests/test_functions.py
napari_bleach_correct/_tests/test_sample_data.py
napari_bleach_correct/modules/__init__.py
napari_bleach_correct/modules/exponential.py
napari_bleach_correct/modules/histogram.py
napari_bleach_correct/modules/ratio.py
napari_bleach_correct-0.0.1.dist-info/LICENSE
napari_bleach_correct-0.0.1.dist-info/METADATA
napari_bleach_correct-0.0.1.dist-info/WHEEL
napari_bleach_correct-0.0.1.dist-info/entry_points.txt
napari_bleach_correct-0.0.1.dist-info/top_level.txt
napari_bleach_correct-0.0.1.dist-info/RECORD
