Metadata-Version: 2.1
Name: napari-bleach-correct
Version: 0.0.1
Summary: A napari plugin to correct time-lapse images for photobleaching.
Home-page: https://github.com/marx-alex/napari-bleach-correct
Author: Alexander Marx
Author-email: a.marx95@gmx.de
License: MIT
Project-URL: Bug Tracker, https://github.com/marx-alex/napari-bleach-correct/issues
Project-URL: Documentation, https://github.com/marx-alex/napari-bleach-correct#README.md
Project-URL: Source Code, https://github.com/marx-alex/napari-bleach-correct
Project-URL: User Support, https://github.com/marx-alex/napari-bleach-correct/issues
Classifier: Development Status :: 2 - Pre-Alpha
Classifier: Intended Audience :: Developers
Classifier: Framework :: napari
Classifier: Topic :: Software Development :: Testing
Classifier: Programming Language :: Python
Classifier: Programming Language :: Python :: 3
Classifier: Programming Language :: Python :: 3.8
Classifier: Programming Language :: Python :: 3.9
Classifier: Programming Language :: Python :: 3.10
Classifier: Operating System :: OS Independent
Classifier: License :: OSI Approved :: MIT License
Requires-Python: >=3.8
License-File: LICENSE
Requires-Dist: numpy
Requires-Dist: magicgui
Requires-Dist: qtpy
Requires-Dist: scikit-image
Requires-Dist: scipy
Requires-Dist: pyqtgraph
Provides-Extra: testing
Requires-Dist: tox ; extra == 'testing'
Requires-Dist: pytest ; extra == 'testing'
Requires-Dist: pytest-cov ; extra == 'testing'
Requires-Dist: pytest-qt ; extra == 'testing'
Requires-Dist: napari ; extra == 'testing'
Requires-Dist: pyqt5 ; extra == 'testing'
